zetapy/__init__.py
zetapy/dependencies.py
zetapy/example.py
zetapy/ifr_dependencies.py
zetapy/main.py
zetapy/plot_dependencies.py
zetapy/test_zetatest.py
zetapy/ts_dependencies.py
zetapy/legacy/__init__.py
zetapy/legacy/dependencies.py
zetapy/legacy/example.py
zetapy/legacy/main.py
zetapy/legacy/msd.py
zetapy-3.2.3.dist-info/licenses/LICENSE
zetapy-3.2.3.dist-info/METADATA
zetapy-3.2.3.dist-info/WHEEL
zetapy-3.2.3.dist-info/top_level.txt
zetapy-3.2.3.dist-info/RECORD
