Metadata-Version: 2.4
Name: zetapy
Version: 3.2.3
Summary: Implementations of the ZETA family of statistical tests.
Home-page: https://github.com/JorritMontijn/zetapy
Author: Jorrit Montijn, Guido Meijer & Alexander Heimel
Author-email: j.s.montijn@gmail.com
License: GPL-3.0-only
Classifier: Programming Language :: Python :: 3
Classifier: Programming Language :: Python :: 3.7
Classifier: Programming Language :: Python :: 3.8
Classifier: Programming Language :: Python :: 3.9
Classifier: Programming Language :: Python :: 3.10
Classifier: Programming Language :: Python :: 3.11
Classifier: License :: OSI Approved :: GNU General Public License v3 (GPLv3)
License-File: LICENSE
Requires-Dist: scipy>=1.1.0
Requires-Dist: numpy
Requires-Dist: matplotlib
Dynamic: author
Dynamic: author-email
Dynamic: classifier
Dynamic: home-page
Dynamic: license
Dynamic: license-file
Dynamic: requires-dist
Dynamic: summary
